{
  "documentsIDs" : {
    "https://www.thetvdb.com/series/gravity-falls" : "ADcW7A==",
    "https://www.tvguide.com/tvshows/better-call-saul/590385/" : "ADcW0w==",
    "https://www.themoviedb.org/tv/1421-modern-family?language=en-US" : "ADcWxg==",
    "https://www.metacritic.com/tv/weeds" : "ADcWfw==",
    "https://www.imdb.com/title/tt1819545/?ref_=nv_sr_1" : "ADcWqQ==",
    "https://www.tvguide.com/tvshows/the-rain/1165673/" : "ADcWyw==",
    "https://www.metacritic.com/tv/altered-carbon" : "ADcWgQ==",
    "https://www.metacritic.com/tv/narcos-mexico" : "ADcWeA==",
    "https://www.rottentomatoes.com/tv/how_i_met_your_mother" : "ADcWiw==",
    "https://www.themoviedb.org/tv/1399-game-of-thrones?language=en-US" : "ADcWuA==",
    "https://trakt.tv/shows/nikita" : "ADcW2w==",
    "https://trakt.tv/shows/vikings" : "ADcW3Q==",
    "https://www.rottentomatoes.com/tv/the_blacklist" : "ADcWlA==",
    "https://www.metacritic.com/tv/suits" : "ADcWfQ==",
    "https://www.rottentomatoes.com/tv/the_good_doctor/" : "ADcWiA==",
    "https://www.imdb.com/title/tt0475784/?ref_=nv_sr_1" : "ADcWnw==",
    "https://www.imdb.com/title/tt1845307/?ref_=nv_sr_1" : "ADcWpw==",
    "https://www.rottentomatoes.com/tv/will_grace?" : "ADcWkA==",
    "http://www.tv.com/shows/law-order/" : "ADcW7Q==",
    "https://www.imdb.com/title/tt6315640/?ref_=nv_sr_1" : "ADcWpA==",
    "https://www.themoviedb.org/tv/1668-friends?language=en-US" : "ADcWuw==",
    "http://www.tv.com/shows/blackish/" : "ADcW7g==",
    "http://www.tv.com/shows/buffy-the-vampire-slayer/" : "ADcW8A==",
    "https://www.tvguide.com/tvshows/altered-carbon/1040368/" : "ADcWyg==",
    "https://www.thetvdb.com/series/stranger-things" : "ADcW5w==",
    "https://www.rottentomatoes.com/tv/skins_uk_" : "ADcWmg==",
    "https://www.metacritic.com/tv/bojack-horseman" : "ADcWew==",
    "https://www.imdb.com/title/tt0903747/?ref_=nv_sr_1" : "ADcWow==",
    "https://www.imdb.com/title/tt0496424/?ref_=nv_sr_2" : "ADcWrw==",
    "https://www.thetvdb.com/series/modern-family" : "ADcW6g==",
    "https://trakt.tv/shows/friends" : "ADcW2Q==",
    "https://www.imdb.com/title/tt1844624/?ref_=nv_sr_2" : "ADcWog==",
    "https://www.rottentomatoes.com/tv/the_o_c_" : "ADcWlw==",
    "https://www.tvguide.com/tvshows/skins/309170/" : "ADcWxw==",
    "https://www.themoviedb.org/tv/1402-the-walking-dead?language=en-US" : "ADcWvA==",
    "https://www.imdb.com/title/tt6048596/?ref_=nv_sr_1" : "ADcWqA==",
    "https://www.rottentomatoes.com/tv/westworld" : "ADcWjg==",
    "https://www.rottentomatoes.com/tv/the_big_bang_theory" : "ADcWnA==",
    "https://trakt.tv/shows/westworld" : "ADcW1w==",
    "https://www.imdb.com/title/tt7549864/" : "ADcWnQ==",
    "https://trakt.tv/shows/mr-robot" : "ADcW4Q==",
    "https://www.thetvdb.com/series/general-hospital" : "ADcW6Q==",
    "https://trakt.tv/shows/3-2016" : "ADcW4g==",
    "https://www.rottentomatoes.com/tv/bull/" : "ADcWig==",
    "https://www.metacritic.com/tv/breaking-bad" : "ADcWeQ==",
    "https://trakt.tv/shows/money-heist" : "ADcW3A==",
    "https://www.tvguide.com/tvshows/nikita/304040/" : "ADcWzA==",
    "https://www.tvguide.com/tvshows/la-casa-de-papel/1155946/" : "ADcWyA==",
    "https://www.thetvdb.com/series/supergirl" : "ADcW5Q==",
    "http://www.tv.com/shows/will-and-grace/" : "ADcW9Q==",
    "https://trakt.tv/shows/the-good-doctor" : "ADcW2A==",
    "https://www.themoviedb.org/tv/1408-house?language=en-US" : "ADcWwA==",
    "https://www.themoviedb.org/tv/1425-house-of-cards?language=en-US" : "ADcWwQ==",
    "https://www.tvguide.com/tvshows/new-girl/325438/" : "ADcW0g==",
    "https://trakt.tv/shows/brooklyn-nine-nine" : "ADcW2g==",
    "https://www.rottentomatoes.com/tv/vikings_2013" : "ADcWkw==",
    "https://www.metacritic.com/tv/the-simpsons" : "ADcWfg==",
    "https://www.imdb.com/title/tt0098800/?ref_=nv_sr_1" : "ADcWrg==",
    "https://www.rottentomatoes.com/tv/grey_s_anatomy" : "ADcWlg==",
    "https://www.imdb.com/title/tt0460637/?ref_=nv_sr_1" : "ADcWpQ==",
    "http://www.tv.com/shows/greys-anatomy/" : "ADcW7w==",
    "https://www.rottentomatoes.com/tv/alcatraz_the_complete_series/s01" : "ADcWmw==",
    "https://www.tvguide.com/tvshows/house/100213/" : "ADcWzg==",
    "https://www.metacritic.com/tv/gossip-girl" : "ADcWdg==",
    "https://www.imdb.com/title/tt2628232/?ref_=nv_sr_1" : "ADcWsg==",
    "https://trakt.tv/shows/santa-clarita-diet" : "ADcW3w==",
    "https://www.imdb.com/title/tt0460649/?ref_=nv_sr_1" : "ADcWoA==",
    "https://www.metacritic.com/tv/freaks-and-geeks" : "ADcWfA==",
    "https://www.metacritic.com/tv/westworld" : "ADcWdQ==",
    "https://trakt.tv/shows/arrow" : "ADcW4w==",
    "https://www.imdb.com/title/tt0944947/?ref_=nv_sr_1" : "ADcWng==",
    "https://www.tvguide.com/tvshows/arrow/375406/" : "ADcW1A==",
    "http://www.tv.com/shows/the-simpsons/" : "ADcW8w==",
    "https://www.imdb.com/title/tt3061046/?ref_=nv_sr_2" : "ADcWsQ==",
    "https://www.thetvdb.com/series/lost" : "ADcW5A==",
    "https://www.thetvdb.com/series/izombie" : "ADcW6A==",
    "https://www.metacritic.com/tv/house-of-cards-2013" : "ADcWeg==",
    "https://www.metacritic.com/tv/stranger-things" : "ADcWhA==",
    "https://www.rottentomatoes.com/tv/once_upon_a_time" : "ADcWkQ==",
    "https://trakt.tv/shows/game-of-thrones" : "ADcW1g==",
    "https://www.themoviedb.org/tv/69050-riverdale?language=en-US" : "ADcWvg==",
    "https://www.imdb.com/title/tt5834204/?ref_=nv_sr_1" : "ADcWtQ==",
    "https://www.tvguide.com/tvshows/desperate-housewives/100118/" : "ADcWzQ==",
    "https://www.rottentomatoes.com/tv/the_oa" : "ADcWmA==",
    "https://www.imdb.com/title/tt5707802/?ref_=nv_sr_1" : "ADcWrA==",
    "https://www.tvguide.com/tvshows/the-flash/644014/" : "ADcW0A==",
    "https://www.rottentomatoes.com/tv/pretty_little_liars" : "ADcWkg==",
    "https://www.imdb.com/title/tt0229889/?ref_=nv_sr_2" : "ADcWpg==",
    "https://www.rottentomatoes.com/tv/the_big_bang_theory/" : "ADcWhw==",
    "http://www.tv.com/shows/doctor-who-2005/" : "ADcW8g==",
    "https://www.rottentomatoes.com/tv/the_voice/" : "ADcWhg==",
    "https://www.tvguide.com/tvshows/everybody-hates-chris/192250/" : "ADcW1Q==",
    "https://www.themoviedb.org/tv/63174-lucifer?language=en-US" : "ADcWww==",
    "https://www.rottentomatoes.com/tv/how_to_get_away_with_murder" : "ADcWjA==",
    "https://www.rottentomatoes.com/tv/better_call_saul/" : "ADcWhQ==",
    "https://www.metacritic.com/tv/anne-with-an-e" : "ADcWdA==",
    "https://www.themoviedb.org/tv/46786-bates-motel?language=en-US" : "ADcWxA==",
    "https://www.imdb.com/title/tt0898266/?ref_=nv_sr_1" : "ADcWsA==",
    "https://www.metacritic.com/tv/orphan-black" : "ADcWgg==",
    "https://www.metacritic.com/tv/the-following" : "ADcWgA==",
    "https://www.metacritic.com/tv/gilmore-girls" : "ADcWdw==",
    "https://www.tvguide.com/tvshows/gotham/638885/" : "ADcWzw==",
    "https://www.themoviedb.org/tv/19885-sherlock?language=en-US" : "ADcWwg==",
    "https://www.thetvdb.com/series/game-of-thrones" : "ADcW5g==",
    "https://www.imdb.com/title/tt2649356/?ref_=nv_sr_1" : "ADcWtA==",
    "https://www.themoviedb.org/tv/63247-westworld?language=en-US" : "ADcWuQ==",
    "https://www.rottentomatoes.com/tv/young_sheldon/" : "ADcWiQ==",
    "http://www.tv.com/shows/the-big-bang-theory/" : "ADcW6w==",
    "http://www.tv.com/shows/days-of-our-lives/" : "ADcW9A==",
    "https://www.tvguide.com/tvshows/3/874982/" : "ADcWyQ==",
    "https://www.metacritic.com/tv/the-good-wife" : "ADcWgw==",
    "https://trakt.tv/shows/the-big-bang-theory" : "ADcW4A==",
    "https://www.themoviedb.org/tv/10545-true-blood?language=en-US" : "ADcWvQ==",
    "https://www.rottentomatoes.com/tv/scrubs" : "ADcWlQ==",
    "https://www.imdb.com/title/tt2085059/?ref_=nv_sr_1" : "ADcWqw==",
    "https://www.themoviedb.org/tv/1434-family-guy?language=en-US" : "ADcWxQ==",
    "https://www.imdb.com/title/tt2372162/?ref_=nv_sr_1" : "ADcWtg==",
    "https://www.themoviedb.org/tv/1100-how-i-met-your-mother?language=en-US" : "ADcWug==",
    "https://www.imdb.com/title/tt3655448/?ref_=nv_sr_1" : "ADcWsw==",
    "https://www.imdb.com/title/tt0362359/?ref_=nv_sr_1" : "ADcWtw==",
    "https://www.themoviedb.org/tv/61664-sense8?language=en-US" : "ADcWvw==",
    "https://www.rottentomatoes.com/tv/flash" : "ADcWmQ==",
    "https://www.imdb.com/title/tt0273855/?ref_=nv_sr_2" : "ADcWrQ==",
    "https://www.imdb.com/title/tt0108778/?ref_=nv_sr_1" : "ADcWoQ==",
    "http://www.tv.com/shows/supernatural/" : "ADcW8Q==",
    "https://www.imdb.com/title/tt5420376/?ref_=nv_sr_1" : "ADcWqg==",
    "https://trakt.tv/shows/desperate-housewives" : "ADcW3g==",
    "https://www.rottentomatoes.com/tv/game_of_thrones?" : "ADcWjQ==",
    "https://www.rottentomatoes.com/tv/mr_robot" : "ADcWjw==",
    "https://www.tvguide.com/tvshows/gossip-girl/288136/" : "ADcW0Q=="
  }
}